articles/__init__.py
articles/cache.py
articles/engine.py
articles/rfeed.py
articles-0.1.0.dist-info/METADATA
articles-0.1.0.dist-info/WHEEL
articles-0.1.0.dist-info/top_level.txt
articles-0.1.0.dist-info/RECORD
