Metadata-Version: 2.1
Name: articles
Version: 0.1.0
Summary: An extremely simple blog engine based on Markdown files
Home-page: https://github.com/svpino/articles
Author: Santiago L. Valdarrama
Author-email: svpino@gmail.com
License: MIT
Platform: UNKNOWN
Classifier: License :: OSI Approved :: MIT License
Classifier: Programming Language :: Python :: 3
Classifier: Programming Language :: Python :: 3.7
Requires-Dist: markdown
Requires-Dist: pygments
